.gitignore
CHANGES.txt
CONTRIBUTORS.txt
COPYRIGHT.txt
LICENSE.txt
README.rst
TODO.txt
setup.cfg
setup.py
tox.ini
docs/.gitignore
docs/Makefile
docs/api.rst
docs/changes.rst
docs/conf.py
docs/index.rst
docs/_static/exclaim.png
docs/_static/exclaim_color.png
docs/_static/info.png
docs/_static/info_color.png
docs/_static/onebit_36.png
docs/_static/onebit_38.png
docs/_static/pyramid.png
docs/_static/pyramid_epub.css
pyramid_deform/__init__.py
pyramid_deform/tests.py
pyramid_deform.egg-info/PKG-INFO
pyramid_deform.egg-info/SOURCES.txt
pyramid_deform.egg-info/dependency_links.txt
pyramid_deform.egg-info/entry_points.txt
pyramid_deform.egg-info/not-zip-safe
pyramid_deform.egg-info/requires.txt
pyramid_deform.egg-info/top_level.txt