Metadata-Version: 1.1
Name: pyramid-deform
Version: 0.2
Summary: Bindings to the Deform form library for the Pyramid web framework
Home-page: http://docs.pylonshq.com
Author: Chris McDonough, Agendaless Consulting
Author-email: pylons-discuss@googlegroups.com
License: BSD-derived (http://www.repoze.org/LICENSE.txt)
Keywords: web wsgi pyramid pylons deform forms form
Platform: UNKNOWN
Classifier: Intended Audience :: Developers
Classifier: Programming Language :: Python
Classifier: Programming Language :: Python :: 2.6
Classifier: Programming Language :: Python :: 2.7
Classifier: Programming Language :: Python :: 3
Classifier: Programming Language :: Python :: 3.2
Classifier: Programming Language :: Python :: Implementation :: CPython
Classifier: Framework :: Pyramid
